pyanylist/__init__.py
pyanylist/__init__.pyi
pyanylist/py.typed
pyanylist/pyanylist.cpython-312-darwin.so
pyanylist-0.0.5.dist-info/METADATA
pyanylist-0.0.5.dist-info/WHEEL
pyanylist-0.0.5.dist-info/licenses/LICENSE
pyanylist-0.0.5.dist-info/RECORD
