Metadata-Version: 2.4
Name: pyanylist
Version: 0.0.5
Classifier: Development Status :: 3 - Alpha
Classifier: Intended Audience :: Developers
Classifier: License :: OSI Approved :: MIT License
Classifier: Programming Language :: Python :: 3
Classifier: Programming Language :: Python :: 3.12
Classifier: Programming Language :: Python :: 3.13
Classifier: Programming Language :: Rust
Requires-Dist: maturin>=1.0 ; extra == 'dev'
Requires-Dist: pytest>=8.0 ; extra == 'dev'
Requires-Dist: pytest-cov>=4.0 ; extra == 'dev'
Requires-Dist: ruff>=0.8.0 ; extra == 'dev'
Requires-Dist: basedpyright>=1.20.0 ; extra == 'dev'
Provides-Extra: dev
License-File: LICENSE
Summary: Python bindings for AnyList API via anylist_rs
Keywords: anylist,shopping,groceries,api,rust
License: MIT
Requires-Python: >=3.12
Project-URL: Homepage, https://github.com/ozonejunkieau/pyanylist
Project-URL: Issues, https://github.com/ozonejunkieau/pyanylist/issues
Project-URL: Repository, https://github.com/ozonejunkieau/pyanylist
